memory_reg.sv
`ifndef MEMORY_REG_SV_INCLUDED
`define MEMORY_REG_SV_INCLUDED

`define MEM_SIZE (1024*512)
`define START 64'h2000

module memory(
    input clk,
    input reset,
    input [63:0] PC,
    output [31:0] instruction,
    // 64-byte instruction fetch port (16 x 32-bit instructions)
    input [63:0] instr_fetch_addr,
    output [511:0] instr_fetch_data,
    input [63:0] data_address,
    output [63:0] data_out,
    output data_ready,
    input write_enable,
    input [63:0] write_address,
    input [63:0] write_data
);
    reg [7:0] bytes [0:`MEM_SIZE-1];

    assign instruction = {bytes[PC + 3], bytes[PC + 2], bytes[PC + 1], bytes[PC]};

    // 64-byte fetch: 16 consecutive 32-bit instructions (little-endian)
    genvar gi;
    generate
        for (gi = 0; gi < 16; gi = gi + 1) begin : fetch_gen
            assign instr_fetch_data[gi*32 +: 32] = {
                bytes[instr_fetch_addr + gi*4 + 3],
                bytes[instr_fetch_addr + gi*4 + 2],
                bytes[instr_fetch_addr + gi*4 + 1],
                bytes[instr_fetch_addr + gi*4]
            };
        end
    endgenerate

    assign data_out = {bytes[data_address + 7], bytes[data_address + 6],
                       bytes[data_address + 5], bytes[data_address + 4],
                       bytes[data_address + 3], bytes[data_address + 2],
                       bytes[data_address + 1], bytes[data_address]};

    assign data_ready = 1'b1;

    always @(posedge clk) begin
        if (write_enable) begin
            bytes[write_address] <= write_data[7:0];
            bytes[write_address + 1] <= write_data[15:8];
            bytes[write_address + 2] <= write_data[23:16];
            bytes[write_address + 3] <= write_data[31:24];
            bytes[write_address + 4] <= write_data[39:32];
            bytes[write_address + 5] <= write_data[47:40];
            bytes[write_address + 6] <= write_data[55:48];
            bytes[write_address + 7] <= write_data[63:56];
        end
    end
endmodule

module reg_file(
    input clk,
    input reset,
    input write_enable,
    input [63:0] write_data,
    input [4:0] write_select,
    input write_enable2,
    input [63:0] write_data2,
    input [4:0] write_select2,
    input [4:0] read_sel1,
    input [4:0] read_sel2,
    input [4:0] read_sel3,
    input [4:0] read_sel4,
    output [63:0] read_data1,
    output [63:0] read_data2,
    output [63:0] read_data3,
    output [63:0] read_data4,
    output [63:0] read_r31
);
    reg [63:0] registers [0:31];

    assign read_data1 = registers[read_sel1];
    assign read_data2 = registers[read_sel2];
    assign read_data3 = registers[read_sel3];
    assign read_data4 = registers[read_sel4];
    assign read_r31 = registers[31];

    integer i;
    always @(posedge clk or posedge reset) begin
        if (reset) begin
            for (i = 0; i < 31; i = i + 1) begin
                registers[i] <= 64'b0;
            end
            registers[31] <= `MEM_SIZE;
        end else begin
            // Port 1 write
            if (write_enable)
                registers[write_select] <= write_data;
            // Port 2 write (wins on conflict with port 1)
            if (write_enable2)
                registers[write_select2] <= write_data2;
        end
    end
endmodule

`endif // MEMORY_REG_SV_INCLUDED

memory_reg_tb.sv
`include "memory_reg.sv"

module memory_reg_tb;
    reg clk, reset;

    // reg_file signals
    reg         rf_we, rf_we2;
    reg  [63:0] rf_wdata, rf_wdata2;
    reg  [4:0]  rf_wsel, rf_wsel2, rf_rs1, rf_rs2, rf_rs3, rf_rs4;
    wire [63:0] rf_rd1, rf_rd2, rf_rd3, rf_rd4, rf_r31;

    reg_file rf(
        .clk(clk), .reset(reset),
        .write_enable(rf_we), .write_data(rf_wdata), .write_select(rf_wsel),
        .write_enable2(rf_we2), .write_data2(rf_wdata2), .write_select2(rf_wsel2),
        .read_sel1(rf_rs1), .read_sel2(rf_rs2), .read_sel3(rf_rs3), .read_sel4(rf_rs4),
        .read_data1(rf_rd1), .read_data2(rf_rd2), .read_data3(rf_rd3), .read_data4(rf_rd4),
        .read_r31(rf_r31)
    );

    // memory signals
    reg  [63:0] PC;
    reg  [63:0] fetch_addr;
    wire [511:0] fetch_data;
    reg  [63:0] data_addr, wr_addr, wr_data;
    reg         mem_we;
    wire [31:0] instr;
    wire [63:0] mem_out;
    wire        mem_rdy;

    memory mem(
        .clk(clk), .reset(reset),
        .PC(PC), .instruction(instr),
        .instr_fetch_addr(fetch_addr), .instr_fetch_data(fetch_data),
        .data_address(data_addr), .data_out(mem_out), .data_ready(mem_rdy),
        .write_enable(mem_we), .write_address(wr_addr), .write_data(wr_data)
    );

    always #5 clk = ~clk;

    integer pass_count, fail_count;

    task check(input [63:0] got, input [63:0] expected, input [255:0] name);
        if (got === expected) begin
            $display("PASS %0s", name);
            pass_count = pass_count + 1;
        end else begin
            $display("FAIL %0s: got %h, expected %h", name, got, expected);
            fail_count = fail_count + 1;
        end
    endtask

    initial begin
        $dumpfile("memory_reg_tb.vcd");
        $dumpvars(0, memory_reg_tb);

        clk = 0; reset = 1;
        rf_we = 0; rf_wdata = 0; rf_wsel = 0;
        rf_we2 = 0; rf_wdata2 = 0; rf_wsel2 = 0;
        rf_rs1 = 0; rf_rs2 = 0; rf_rs3 = 0; rf_rs4 = 0;
        mem_we = 0; wr_addr = 0; wr_data = 0; data_addr = 0;
        PC = 64'h2000; fetch_addr = 64'h2000;
        pass_count = 0; fail_count = 0;

        #10 reset = 0;

        // ===== reg_file tests =====

        // Task 1.3: r31 == MEM_SIZE after reset
        check(rf_r31, `MEM_SIZE, "r31 init");

        // Original test: write/read single port
        @(negedge clk);
        rf_we = 1; rf_wsel = 5'd5; rf_wdata = 64'hDEADBEEF;
        @(negedge clk);
        rf_we = 0; rf_rs1 = 5'd5;
        #1;
        check(rf_rd1, 64'hDEADBEEF, "reg write/read port1");

        // Task 1.2: 4th read port
        rf_rs4 = 5'd5;
        #1;
        check(rf_rd4, 64'hDEADBEEF, "read port4");

        // Task 1.2: 2nd write port
        @(negedge clk);
        rf_we2 = 1; rf_wsel2 = 5'd10; rf_wdata2 = 64'hCAFEBABE;
        @(negedge clk);
        rf_we2 = 0; rf_rs2 = 5'd10;
        #1;
        check(rf_rd2, 64'hCAFEBABE, "write port2");

        // Task 1.2: simultaneous writes to different registers
        @(negedge clk);
        rf_we = 1; rf_wsel = 5'd1; rf_wdata = 64'h1111;
        rf_we2 = 1; rf_wsel2 = 5'd2; rf_wdata2 = 64'h2222;
        @(negedge clk);
        rf_we = 0; rf_we2 = 0;
        rf_rs1 = 5'd1; rf_rs2 = 5'd2;
        #1;
        check(rf_rd1, 64'h1111, "dual write reg1");
        check(rf_rd2, 64'h2222, "dual write reg2");

        // Task 1.2: simultaneous writes to SAME register (port 2 wins)
        @(negedge clk);
        rf_we = 1; rf_wsel = 5'd7; rf_wdata = 64'hAAAA;
        rf_we2 = 1; rf_wsel2 = 5'd7; rf_wdata2 = 64'hBBBB;
        @(negedge clk);
        rf_we = 0; rf_we2 = 0;
        rf_rs1 = 5'd7;
        #1;
        check(rf_rd1, 64'hBBBB, "same-reg conflict port2 wins");

        // Task 1.3: r31 still correct after writes
        check(rf_r31, `MEM_SIZE, "r31 preserved");

        // ===== memory tests =====

        // Original test: write/read data port
        @(negedge clk);
        mem_we = 1; wr_addr = 64'h100; wr_data = 64'h1122334455667788;
        @(negedge clk);
        mem_we = 0; data_addr = 64'h100;
        #1;
        check(mem_out, 64'h1122334455667788, "mem write/read");

        // Task 1.1: 64-byte instruction fetch port
        // Store 16 known 32-bit words at address 0x3000
        @(negedge clk);
        mem_we = 1; wr_addr = 64'h3000; wr_data = {32'h0, 32'hAABBCCDD};
        @(negedge clk);
        wr_addr = 64'h3008; wr_data = {32'h0, 32'h11223344};
        @(negedge clk);
        mem_we = 0;

        fetch_addr = 64'h3000;
        #1;
        // First 32-bit word at offset 0
        check({32'h0, fetch_data[31:0]}, {32'h0, 32'hAABBCCDD}, "fetch word 0");
        // Second 32-bit word at offset 4
        check({32'h0, fetch_data[63:32]}, {32'h0, 32'h00000000}, "fetch word 1");
        // Third 32-bit word at offset 8
        check({32'h0, fetch_data[95:64]}, {32'h0, 32'h11223344}, "fetch word 2");

        // ===== Summary =====
        $display("\n--- Results: %0d passed, %0d failed ---", pass_count, fail_count);
        $finish;
    end
endmodule

memory_reg_tb.vcd
$date
	Mon Apr 13 18:02:30 2026
$end
$version
	Icarus Verilog
$end
$timescale
	1s
$end
$scope module memory_reg_tb $end
$var wire 1 ! mem_rdy $end
$var wire 64 " rf_rd4 [63:0] $end
$var wire 64 # rf_rd3 [63:0] $end
$var wire 64 $ rf_rd2 [63:0] $end
$var wire 64 % rf_rd1 [63:0] $end
$var wire 64 & rf_r31 [63:0] $end
$var wire 64 ' mem_out [63:0] $end
$var wire 32 ( instr [31:0] $end
$var wire 512 ) fetch_data [511:0] $end
$var reg 64 * PC [63:0] $end
$var reg 1 + clk $end
$var reg 64 , data_addr [63:0] $end
$var reg 64 - fetch_addr [63:0] $end
$var reg 1 . mem_we $end
$var reg 1 / reset $end
$var reg 5 0 rf_rs1 [4:0] $end
$var reg 5 1 rf_rs2 [4:0] $end
$var reg 5 2 rf_rs3 [4:0] $end
$var reg 5 3 rf_rs4 [4:0] $end
$var reg 64 4 rf_wdata [63:0] $end
$var reg 64 5 rf_wdata2 [63:0] $end
$var reg 1 6 rf_we $end
$var reg 1 7 rf_we2 $end
$var reg 5 8 rf_wsel [4:0] $end
$var reg 5 9 rf_wsel2 [4:0] $end
$var reg 64 : wr_addr [63:0] $end
$var reg 64 ; wr_data [63:0] $end
$var integer 32 < fail_count [31:0] $end
$var integer 32 = pass_count [31:0] $end
$scope module mem $end
$var wire 64 > PC [63:0] $end
$var wire 1 + clk $end
$var wire 64 ? data_address [63:0] $end
$var wire 1 ! data_ready $end
$var wire 64 @ instr_fetch_addr [63:0] $end
$var wire 1 / reset $end
$var wire 64 A write_address [63:0] $end
$var wire 64 B write_data [63:0] $end
$var wire 1 . write_enable $end
$var wire 32 C instruction [31:0] $end
$var wire 512 D instr_fetch_data [511:0] $end
$var wire 64 E data_out [63:0] $end
$scope begin fetch_gen[0] $end
$var parameter 2 F gi $end
$upscope $end
$scope begin fetch_gen[1] $end
$var parameter 2 G gi $end
$upscope $end
$scope begin fetch_gen[2] $end
$var parameter 3 H gi $end
$upscope $end
$scope begin fetch_gen[3] $end
$var parameter 3 I gi $end
$upscope $end
$scope begin fetch_gen[4] $end
$var parameter 4 J gi $end
$upscope $end
$scope begin fetch_gen[5] $end
$var parameter 4 K gi $end
$upscope $end
$scope begin fetch_gen[6] $end
$var parameter 4 L gi $end
$upscope $end
$scope begin fetch_gen[7] $end
$var parameter 4 M gi $end
$upscope $end
$scope begin fetch_gen[8] $end
$var parameter 5 N gi $end
$upscope $end
$scope begin fetch_gen[9] $end
$var parameter 5 O gi $end
$upscope $end
$scope begin fetch_gen[10] $end
$var parameter 5 P gi $end
$upscope $end
$scope begin fetch_gen[11] $end
$var parameter 5 Q gi $end
$upscope $end
$scope begin fetch_gen[12] $end
$var parameter 5 R gi $end
$upscope $end
$scope begin fetch_gen[13] $end
$var parameter 5 S gi $end
$upscope $end
$scope begin fetch_gen[14] $end
$var parameter 5 T gi $end
$upscope $end
$scope begin fetch_gen[15] $end
$var parameter 5 U gi $end
$upscope $end
$upscope $end
$scope module rf $end
$var wire 1 + clk $end
$var wire 64 V read_data1 [63:0] $end
$var wire 64 W read_data2 [63:0] $end
$var wire 64 X read_data3 [63:0] $end
$var wire 64 Y read_data4 [63:0] $end
$var wire 64 Z read_r31 [63:0] $end
$var wire 5 [ read_sel1 [4:0] $end
$var wire 5 \ read_sel2 [4:0] $end
$var wire 5 ] read_sel3 [4:0] $end
$var wire 5 ^ read_sel4 [4:0] $end
$var wire 1 / reset $end
$var wire 64 _ write_data [63:0] $end
$var wire 64 ` write_data2 [63:0] $end
$var wire 1 6 write_enable $end
$var wire 1 7 write_enable2 $end
$var wire 5 a write_select [4:0] $end
$var wire 5 b write_select2 [4:0] $end
$var integer 32 c i [31:0] $end
$upscope $end
$scope task check $end
$var reg 64 d expected [63:0] $end
$var reg 64 e got [63:0] $end
$var reg 256 f name [255:0] $end
$upscope $end
$upscope $end
$enddefinitions $end
$comment Show the parameter values. $end
$dumpall
b1111 U
b1110 T
b1101 S
b1100 R
b1011 Q
b1010 P
b1001 O
b1000 N
b111 M
b110 L
b101 K
b100 J
b11 I
b10 H
b1 G
b0 F
$end
#0
$dumpvars
bx f
bx e
bx d
b11111 c
b0 b
b0 a
b0 `
b0 _
b0 ^
b0 ]
b0 \
b0 [
b10000000000000000000 Z
b0 Y
b0 X
b0 W
b0 V
bx E
bx D
bx C
b0 B
b0 A
b10000000000000 @
b0 ?
b10000000000000 >
b0 =
b0 <
b0 ;
b0 :
b0 9
b0 8
07
06
b0 5
b0 4
b0 3
b0 2
b0 1
b0 0
1/
0.
b10000000000000 -
b0 ,
0+
b10000000000000 *
bx )
bx (
bx '
b10000000000000000000 &
b0 %
b0 $
b0 #
b0 "
1!
$end
#5
b11111 c
1+
#10
b11011110101011011011111011101111 4
b11011110101011011011111011101111 _
b101 8
b101 a
16
0+
b1 =
b111001000110011001100010010000001101001011011100110100101110100 f
b10000000000000000000 d
b10000000000000000000 e
0/
#15
1+
#20
b11011110101011011011111011101111 %
b11011110101011011011111011101111 V
b101 0
b101 [
06
0+
#21
b11011110101011011011111011101111 "
b11011110101011011011111011101111 Y
b101 3
b101 ^
b10 =
b111001001100101011001110010000001110111011100100110100101110100011001010010111101110010011001010110000101100100001000000111000001101111011100100111010000110001 f
b11011110101011011011111011101111 d
b11011110101011011011111011101111 e
#22
b11 =
b1110010011001010110000101100100001000000111000001101111011100100111010000110100 f
#25
1+
#30
b11001010111111101011101010111110 5
b11001010111111101011101010111110 `
b1010 9
b1010 b
17
0+
#35
1+
#40
b11001010111111101011101010111110 $
b11001010111111101011101010111110 W
b1010 1
b1010 \
07
0+
#41
b100 =
b111011101110010011010010111010001100101001000000111000001101111011100100111010000110010 f
b11001010111111101011101010111110 d
b11001010111111101011101010111110 e
#45
1+
#50
b10001000100010 5
b10001000100010 `
b10 9
b10 b
17
b1000100010001 4
b1000100010001 _
b1 8
b1 a
16
0+
#55
1+
#60
b10001000100010 $
b10001000100010 W
b1000100010001 %
b1000100010001 V
b10 1
b10 \
b1 0
b1 [
07
06
0+
#61
b110 =
b11001000111010101100001011011000010000001110111011100100110100101110100011001010010000001110010011001010110011100110010 f
b10001000100010 d
b10001000100010 e
#65
1+
#70
b1011101110111011 5
b1011101110111011 `
b111 9
b111 b
17
b1010101010101010 4
b1010101010101010 _
b111 8
b111 a
16
0+
#75
1+
#80
b1011101110111011 %
b1011101110111011 V
b111 0
b111 [
07
06
0+
#81
b1000 =
b1110010001100110011000100100000011100000111001001100101011100110110010101110010011101100110010101100100 f
b10000000000000000000 d
b10000000000000000000 e
#85
1+
#90
b1000100100010001100110100010001010101011001100111011110001000 ;
b1000100100010001100110100010001010101011001100111011110001000 B
b100000000 :
b100000000 A
1.
0+
#95
1+
#100
b1000100100010001100110100010001010101011001100111011110001000 '
b1000100100010001100110100010001010101011001100111011110001000 E
b100000000 ,
b100000000 ?
0.
0+
#101
b1001 =
b110110101100101011011010010000001110111011100100110100101110100011001010010111101110010011001010110000101100100 f
b1000100100010001100110100010001010101011001100111011110001000 d
b1000100100010001100110100010001010101011001100111011110001000 e
#105
1+
#110
b10101010101110111100110011011101 ;
b10101010101110111100110011011101 B
b11000000000000 :
b11000000000000 A
1.
0+
#115
1+
#120
b10001001000100011001101000100 ;
b10001001000100011001101000100 B
b11000000001000 :
b11000000001000 A
0+
#125
1+
#130
bx00000000000000000000000000000000000100010010001000110011010001000000000000000000000000000000000010101010101110111100110011011101 )
bx00000000000000000000000000000000000100010010001000110011010001000000000000000000000000000000000010101010101110111100110011011101 D
b11000000000000 -
b11000000000000 @
0.
0+
#131
b1100 =
b11001100110010101110100011000110110100000100000011101110110111101110010011001000010000000110010 f
b10001001000100011001101000100 d
b10001001000100011001101000100 e
