rat.sv
// Register Alias Table (RAT) — 32 entries mapping architectural reg -> physical reg (7-bit).
// Supports dual-issue: 4 source lookups + 2 renames per cycle.
// Handles intra-group forwarding (instruction B reads what instruction A just renamed).
// One checkpoint for branch misprediction recovery.

module rat (
    input         clk,
    input         reset,

    // Source lookups (combinational, 4 ports for dual-issue)
    input  [4:0]  lookup_arch0,     // instr A src1
    output [6:0]  lookup_phys0,
    input  [4:0]  lookup_arch1,     // instr A src2
    output [6:0]  lookup_phys1,
    input  [4:0]  lookup_arch2,     // instr B src1
    output reg [6:0] lookup_phys2,
    input  [4:0]  lookup_arch3,     // instr B src2
    output reg [6:0] lookup_phys3,

    // Rename port A (instruction A, first in program order)
    input         rename_en_a,
    input  [4:0]  rename_arch_a,
    input  [6:0]  rename_phys_a,
    output [6:0]  rename_old_a,

    // Rename port B (instruction B, second in program order)
    input         rename_en_b,
    input  [4:0]  rename_arch_b,
    input  [6:0]  rename_phys_b,
    output reg [6:0] rename_old_b,

    // Checkpoint
    input         checkpoint_en,
    input         restore_en
);

    reg [6:0] table_r [0:31];
    reg [6:0] checkpoint_r [0:31];

    // --- Combinational lookups ---
    // Ports 0,1 for instruction A: read directly from table
    assign lookup_phys0 = table_r[lookup_arch0];
    assign lookup_phys1 = table_r[lookup_arch1];

    // Ports 2,3 for instruction B: intra-group forwarding from A
    always @(*) begin
        if (rename_en_a && lookup_arch2 == rename_arch_a)
            lookup_phys2 = rename_phys_a;
        else
            lookup_phys2 = table_r[lookup_arch2];
    end

    always @(*) begin
        if (rename_en_a && lookup_arch3 == rename_arch_a)
            lookup_phys3 = rename_phys_a;
        else
            lookup_phys3 = table_r[lookup_arch3];
    end

    // --- Old mapping outputs ---
    assign rename_old_a = table_r[rename_arch_a];

    // For B: if A renames the same arch reg, B's "old" is A's *new* mapping
    always @(*) begin
        if (rename_en_a && rename_arch_b == rename_arch_a)
            rename_old_b = rename_phys_a;
        else
            rename_old_b = table_r[rename_arch_b];
    end

    // --- Sequential: rename + checkpoint/restore ---
    integer i;
    always @(posedge clk or posedge reset) begin
        if (reset) begin
            for (i = 0; i < 32; i = i + 1) begin
                table_r[i]      <= i[6:0];
                checkpoint_r[i] <= i[6:0];
            end
        end else if (restore_en) begin
            for (i = 0; i < 32; i = i + 1)
                table_r[i] <= checkpoint_r[i];
        end else begin
            // Rename A first, then B (program order)
            if (rename_en_a)
                table_r[rename_arch_a] <= rename_phys_a;
            if (rename_en_b)
                table_r[rename_arch_b] <= rename_phys_b;

            // Checkpoint: snapshot current state including this cycle's renames
            if (checkpoint_en) begin
                for (i = 0; i < 32; i = i + 1)
                    checkpoint_r[i] <= table_r[i];
                if (rename_en_a)
                    checkpoint_r[rename_arch_a] <= rename_phys_a;
                if (rename_en_b)
                    checkpoint_r[rename_arch_b] <= rename_phys_b;
            end
        end
    end

endmodule

phys_reg_file.sv
// Physical Register File — 128 x 64-bit, 4 read ports (combinational), 2 write ports (posedge clk)
// Each register has a "ready" bit indicating the value is valid.

module phys_reg_file (
    input         clk,
    input         reset,

    // Read ports (combinational)
    input  [6:0]  read_addr0,
    output [63:0] read_data0,
    output        read_ready0,

    input  [6:0]  read_addr1,
    output [63:0] read_data1,
    output        read_ready1,

    input  [6:0]  read_addr2,
    output [63:0] read_data2,
    output        read_ready2,

    input  [6:0]  read_addr3,
    output [63:0] read_data3,
    output        read_ready3,

    // Write port 0
    input         write_en0,
    input  [6:0]  write_addr0,
    input  [63:0] write_data0,

    // Write port 1 (wins on conflict with port 0)
    input         write_en1,
    input  [6:0]  write_addr1,
    input  [63:0] write_data1,

    // Clear ready bit (used at rename time to mark destination "not ready")
    input         clear_ready_en0,
    input  [6:0]  clear_ready_addr0,
    input         clear_ready_en1,
    input  [6:0]  clear_ready_addr1
);

    reg [63:0] data  [0:127];
    reg        ready [0:127];

    // Combinational reads
    assign read_data0  = data[read_addr0];
    assign read_ready0 = ready[read_addr0];
    assign read_data1  = data[read_addr1];
    assign read_ready1 = ready[read_addr1];
    assign read_data2  = data[read_addr2];
    assign read_ready2 = ready[read_addr2];
    assign read_data3  = data[read_addr3];
    assign read_ready3 = ready[read_addr3];

    integer i;
    always @(posedge clk or posedge reset) begin
        if (reset) begin
            for (i = 0; i < 128; i = i + 1) begin
                data[i]  <= 64'd0;
                ready[i] <= 1'b1;
            end
        end else begin
            // Clear ready bits first (rename destinations become not-ready)
            if (clear_ready_en0) ready[clear_ready_addr0] <= 1'b0;
            if (clear_ready_en1) ready[clear_ready_addr1] <= 1'b0;

            // Write port 0
            if (write_en0) begin
                data[write_addr0]  <= write_data0;
                ready[write_addr0] <= 1'b1;
            end
            // Write port 1 (wins on conflict)
            if (write_en1) begin
                data[write_addr1]  <= write_data1;
                ready[write_addr1] <= 1'b1;
            end
        end
    end

endmodule

hdl/free_list.sv
`ifndef FREE_LIST_SV_INCLUDED
`define FREE_LIST_SV_INCLUDED

// Free List — circular FIFO of 7-bit physical register indices.
// Capacity: 96 entries (phys regs 32-127 initially free).
// Supports alloc (pop) up to 2 per cycle and free (push) up to 2 per cycle.

module free_list (
    input         clk,
    input         reset,

    // Allocate (pop) interface
    input         alloc_en0,
    input         alloc_en1,
    output [6:0]  alloc_reg0,
    output [6:0]  alloc_reg1,

    // Free (push) interface
    input         free_en0,
    input  [6:0]  free_reg0,
    input         free_en1,
    input  [6:0]  free_reg1,

    // Status
    output        empty,
    output        almost_empty
);

    localparam FIFO_DEPTH = 128;
    localparam PTR_BITS   = 7;

    reg [6:0] fifo [0:FIFO_DEPTH-1];
    reg [PTR_BITS:0] head, tail;
    wire [PTR_BITS:0] count;

    assign count = tail - head;
    assign empty = (count == 0);
    assign almost_empty = (count == 1);

    assign alloc_reg0 = fifo[head[PTR_BITS-1:0]];
    assign alloc_reg1 = fifo[head[PTR_BITS-1:0] + 1];

    integer i;
    always @(posedge clk or posedge reset) begin
        if (reset) begin
            head <= 0;
            tail <= 0;
            for (i = 0; i < 96; i = i + 1) begin
                fifo[i] <= i[6:0] + 7'd32;
            end
            tail <= 8'd96;
        end else begin
            // Allocate (pop from head)
            if (alloc_en0 && alloc_en1 && count >= 2)
                head <= head + 2;
            else if (alloc_en0 && count >= 1)
                head <= head + 1;

            // Free (push to tail)
            if (free_en0 && free_en1) begin
                fifo[tail[PTR_BITS-1:0]]     <= free_reg0;
                fifo[tail[PTR_BITS-1:0] + 1] <= free_reg1;
                tail <= tail + 2;
            end else if (free_en0) begin
                fifo[tail[PTR_BITS-1:0]] <= free_reg0;
                tail <= tail + 1;
            end else if (free_en1) begin
                fifo[tail[PTR_BITS-1:0]] <= free_reg1;
                tail <= tail + 1;
            end
        end
    end

endmodule

`endif // FREE_LIST_SV_INCLUDED

rat_tb.sv
`include "phys_reg_file.sv"
`include "free_list.sv"
`include "rat.sv"

module rat_tb;
    reg clk, reset;

    // ---- Free list signals ----
    reg        fl_alloc0, fl_alloc1;
    wire [6:0] fl_reg0, fl_reg1;
    reg        fl_free0, fl_free1;
    reg  [6:0] fl_free_reg0, fl_free_reg1;
    wire       fl_empty, fl_almost_empty;

    free_list fl (
        .clk(clk), .reset(reset),
        .alloc_en0(fl_alloc0), .alloc_en1(fl_alloc1),
        .alloc_reg0(fl_reg0),  .alloc_reg1(fl_reg1),
        .free_en0(fl_free0),   .free_reg0(fl_free_reg0),
        .free_en1(fl_free1),   .free_reg1(fl_free_reg1),
        .empty(fl_empty),      .almost_empty(fl_almost_empty)
    );

    // ---- Physical register file signals ----
    reg  [6:0]  prf_ra0, prf_ra1, prf_ra2, prf_ra3;
    wire [63:0] prf_rd0, prf_rd1, prf_rd2, prf_rd3;
    wire        prf_rr0, prf_rr1, prf_rr2, prf_rr3;
    reg         prf_we0, prf_we1;
    reg  [6:0]  prf_wa0, prf_wa1;
    reg  [63:0] prf_wd0, prf_wd1;
    reg         prf_cr0, prf_cr1;
    reg  [6:0]  prf_ca0, prf_ca1;

    phys_reg_file prf (
        .clk(clk), .reset(reset),
        .read_addr0(prf_ra0), .read_data0(prf_rd0), .read_ready0(prf_rr0),
        .read_addr1(prf_ra1), .read_data1(prf_rd1), .read_ready1(prf_rr1),
        .read_addr2(prf_ra2), .read_data2(prf_rd2), .read_ready2(prf_rr2),
        .read_addr3(prf_ra3), .read_data3(prf_rd3), .read_ready3(prf_rr3),
        .write_en0(prf_we0), .write_addr0(prf_wa0), .write_data0(prf_wd0),
        .write_en1(prf_we1), .write_addr1(prf_wa1), .write_data1(prf_wd1),
        .clear_ready_en0(prf_cr0), .clear_ready_addr0(prf_ca0),
        .clear_ready_en1(prf_cr1), .clear_ready_addr1(prf_ca1)
    );

    // ---- RAT signals ----
    reg  [4:0] rat_la0, rat_la1, rat_la2, rat_la3;
    wire [6:0] rat_lp0, rat_lp1, rat_lp2, rat_lp3;
    reg        rat_ren_a, rat_ren_b;
    reg  [4:0] rat_ra_a, rat_ra_b;
    reg  [6:0] rat_rp_a, rat_rp_b;
    wire [6:0] rat_old_a, rat_old_b;
    reg        rat_chk, rat_rst;

    rat rat_dut (
        .clk(clk), .reset(reset),
        .lookup_arch0(rat_la0), .lookup_phys0(rat_lp0),
        .lookup_arch1(rat_la1), .lookup_phys1(rat_lp1),
        .lookup_arch2(rat_la2), .lookup_phys2(rat_lp2),
        .lookup_arch3(rat_la3), .lookup_phys3(rat_lp3),
        .rename_en_a(rat_ren_a), .rename_arch_a(rat_ra_a), .rename_phys_a(rat_rp_a), .rename_old_a(rat_old_a),
        .rename_en_b(rat_ren_b), .rename_arch_b(rat_ra_b), .rename_phys_b(rat_rp_b), .rename_old_b(rat_old_b),
        .checkpoint_en(rat_chk), .restore_en(rat_rst)
    );

    always #5 clk = ~clk;

    integer pass_count, fail_count;

    task check(input [63:0] got, input [63:0] expected, input [255:0] name);
        if (got === expected) begin
            $display("PASS %0s", name);
            pass_count = pass_count + 1;
        end else begin
            $display("FAIL %0s: got %0d, expected %0d", name, got, expected);
            fail_count = fail_count + 1;
        end
    endtask

    initial begin
        $dumpfile("rat_tb.vcd");
        $dumpvars(0, rat_tb);

        clk = 0; reset = 1;
        fl_alloc0 = 0; fl_alloc1 = 0;
        fl_free0 = 0; fl_free1 = 0;
        fl_free_reg0 = 0; fl_free_reg1 = 0;
        prf_ra0 = 0; prf_ra1 = 0; prf_ra2 = 0; prf_ra3 = 0;
        prf_we0 = 0; prf_we1 = 0;
        prf_wa0 = 0; prf_wa1 = 0; prf_wd0 = 0; prf_wd1 = 0;
        prf_cr0 = 0; prf_cr1 = 0; prf_ca0 = 0; prf_ca1 = 0;
        rat_la0 = 0; rat_la1 = 0; rat_la2 = 0; rat_la3 = 0;
        rat_ren_a = 0; rat_ren_b = 0;
        rat_ra_a = 0; rat_ra_b = 0; rat_rp_a = 0; rat_rp_b = 0;
        rat_chk = 0; rat_rst = 0;
        pass_count = 0; fail_count = 0;

        #10 reset = 0;

        // ============================================================
        // Physical Register File tests
        // ============================================================

        // After reset, all registers ready
        prf_ra0 = 7'd0; prf_ra1 = 7'd31; prf_ra2 = 7'd50; prf_ra3 = 7'd127;
        #1;
        check({63'd0, prf_rr0}, 64'd1, "prf reg0 ready");
        check({63'd0, prf_rr2}, 64'd1, "prf reg50 ready");
        check(prf_rd0, 64'd0, "prf reg0 value=0");

        // Write to reg 40, then read back
        @(negedge clk);
        prf_we0 = 1; prf_wa0 = 7'd40; prf_wd0 = 64'hFACE;
        @(negedge clk);
        prf_we0 = 0;
        prf_ra0 = 7'd40;
        #1;
        check(prf_rd0, 64'hFACE, "prf write/read");

        // Clear ready, verify it goes low
        @(negedge clk);
        prf_cr0 = 1; prf_ca0 = 7'd60;
        @(negedge clk);
        prf_cr0 = 0;
        prf_ra1 = 7'd60;
        #1;
        check({63'd0, prf_rr1}, 64'd0, "prf clear_ready");

        // Write to same reg restores ready
        @(negedge clk);
        prf_we0 = 1; prf_wa0 = 7'd60; prf_wd0 = 64'hBEEF;
        @(negedge clk);
        prf_we0 = 0;
        prf_ra1 = 7'd60;
        #1;
        check(prf_rd1, 64'hBEEF, "prf write restores ready val");
        check({63'd0, prf_rr1}, 64'd1, "prf write restores ready bit");

        // Dual write: port 1 wins on conflict
        @(negedge clk);
        prf_we0 = 1; prf_wa0 = 7'd70; prf_wd0 = 64'hAAAA;
        prf_we1 = 1; prf_wa1 = 7'd70; prf_wd1 = 64'hBBBB;
        @(negedge clk);
        prf_we0 = 0; prf_we1 = 0;
        prf_ra0 = 7'd70;
        #1;
        check(prf_rd0, 64'hBBBB, "prf dual write conflict port1 wins");

        // ============================================================
        // Free List tests
        // ============================================================

        // After reset: 96 entries, first alloc should give 32
        check({57'd0, fl_reg0}, 64'd32, "fl first alloc_reg0");
        check({57'd0, fl_reg1}, 64'd33, "fl first alloc_reg1");
        check({63'd0, fl_empty}, 64'd0, "fl not empty");

        // Allocate 2
        @(negedge clk);
        fl_alloc0 = 1; fl_alloc1 = 1;
        @(negedge clk);
        fl_alloc0 = 0; fl_alloc1 = 0;
        #1;
        // Next alloc should give 34, 35
        check({57'd0, fl_reg0}, 64'd34, "fl after alloc2 reg0=34");
        check({57'd0, fl_reg1}, 64'd35, "fl after alloc2 reg1=35");

        // Allocate 1 more
        @(negedge clk);
        fl_alloc0 = 1; fl_alloc1 = 0;
        @(negedge clk);
        fl_alloc0 = 0;
        #1;
        check({57'd0, fl_reg0}, 64'd35, "fl after alloc1 reg0=35");

        // Free a register (push 32 back)
        @(negedge clk);
        fl_free0 = 1; fl_free_reg0 = 7'd32;
        @(negedge clk);
        fl_free0 = 0;

        // ============================================================
        // RAT tests
        // ============================================================

        // Identity mapping on reset: arch reg i -> phys reg i
        rat_la0 = 5'd0;  rat_la1 = 5'd5;
        rat_la2 = 5'd31; rat_la3 = 5'd15;
        #1;
        check({57'd0, rat_lp0}, 64'd0,  "rat identity r0->p0");
        check({57'd0, rat_lp1}, 64'd5,  "rat identity r5->p5");
        check({57'd0, rat_lp2}, 64'd31, "rat identity r31->p31");
        check({57'd0, rat_lp3}, 64'd15, "rat identity r15->p15");

        // Single rename: arch r1 -> phys p50
        @(negedge clk);
        rat_ren_a = 1; rat_ra_a = 5'd1; rat_rp_a = 7'd50;
        rat_ren_b = 0;
        @(negedge clk);
        rat_ren_a = 0;
        rat_la0 = 5'd1;
        #1;
        check({57'd0, rat_lp0}, 64'd50, "rat single rename r1->p50");

        // Dual rename: arch r2->p60, arch r3->p70
        @(negedge clk);
        rat_ren_a = 1; rat_ra_a = 5'd2; rat_rp_a = 7'd60;
        rat_ren_b = 1; rat_ra_b = 5'd3; rat_rp_b = 7'd70;
        @(negedge clk);
        rat_ren_a = 0; rat_ren_b = 0;
        rat_la0 = 5'd2; rat_la1 = 5'd3;
        #1;
        check({57'd0, rat_lp0}, 64'd60, "rat dual rename r2->p60");
        check({57'd0, rat_lp1}, 64'd70, "rat dual rename r3->p70");

        // Old mapping output: rename r2 again to p80, should report old=p60
        @(negedge clk);
        rat_ren_a = 1; rat_ra_a = 5'd2; rat_rp_a = 7'd80;
        rat_ren_b = 0;
        #1;
        check({57'd0, rat_old_a}, 64'd60, "rat old mapping r2 was p60");
        @(negedge clk);
        rat_ren_a = 0;

        // Intra-group forwarding: A renames r5->p90, B reads r5 as source
        @(negedge clk);
        rat_ren_a = 1; rat_ra_a = 5'd5; rat_rp_a = 7'd90;
        rat_ren_b = 0;
        rat_la2 = 5'd5;
        #1;
        check({57'd0, rat_lp2}, 64'd90, "rat intra-group fwd B sees A rename");
        @(negedge clk);
        rat_ren_a = 0;

        // Intra-group old_b: A renames r10->p100, B renames r10->p110
        @(negedge clk);
        rat_ren_a = 1; rat_ra_a = 5'd10; rat_rp_a = 7'd100;
        rat_ren_b = 1; rat_ra_b = 5'd10; rat_rp_b = 7'd110;
        #1;
        check({57'd0, rat_old_a}, {57'd0, 7'd10},  "rat old_a r10 was identity p10");
        check({57'd0, rat_old_b}, {57'd0, 7'd100}, "rat old_b r10 is A new p100");
        @(negedge clk);
        rat_ren_a = 0; rat_ren_b = 0;

        // After both renames, r10 should map to p110
        rat_la0 = 5'd10;
        #1;
        check({57'd0, rat_lp0}, 64'd110, "rat r10->p110 after dual rename");

        // Checkpoint / Restore
        @(negedge clk);
        rat_chk = 1;
        @(negedge clk);
        rat_chk = 0;

        // Rename r0 -> p120
        @(negedge clk);
        rat_ren_a = 1; rat_ra_a = 5'd0; rat_rp_a = 7'd120;
        @(negedge clk);
        rat_ren_a = 0;
        rat_la0 = 5'd0;
        #1;
        check({57'd0, rat_lp0}, 64'd120, "rat post-chk rename r0->p120");

        // Restore checkpoint — r0 back to p0
        @(negedge clk);
        rat_rst = 1;
        @(negedge clk);
        rat_rst = 0;
        rat_la0 = 5'd0;
        #1;
        check({57'd0, rat_lp0}, 64'd0, "rat restore r0 back to p0");

        // r10 should still be p110 (checkpointed state)
        rat_la1 = 5'd10;
        #1;
        check({57'd0, rat_lp1}, 64'd110, "rat restore r10 still p110");

        // ============================================================
        $display("\n--- Results: %0d passed, %0d failed ---", pass_count, fail_count);
        $finish;
    end
endmodule

rat_tb.vcd
$date
	Mon Apr 13 18:10:59 2026
$end
$version
	Icarus Verilog
$end
$timescale
	1s
$end
$scope module rat_tb $end
$var wire 7 ! rat_old_b [6:0] $end
$var wire 7 " rat_old_a [6:0] $end
$var wire 7 # rat_lp3 [6:0] $end
$var wire 7 $ rat_lp2 [6:0] $end
$var wire 7 % rat_lp1 [6:0] $end
$var wire 7 & rat_lp0 [6:0] $end
$var wire 1 ' prf_rr3 $end
$var wire 1 ( prf_rr2 $end
$var wire 1 ) prf_rr1 $end
$var wire 1 * prf_rr0 $end
$var wire 64 + prf_rd3 [63:0] $end
$var wire 64 , prf_rd2 [63:0] $end
$var wire 64 - prf_rd1 [63:0] $end
$var wire 64 . prf_rd0 [63:0] $end
$var wire 7 / fl_reg1 [6:0] $end
$var wire 7 0 fl_reg0 [6:0] $end
$var wire 1 1 fl_empty $end
$var wire 1 2 fl_almost_empty $end
$var reg 1 3 clk $end
$var reg 1 4 fl_alloc0 $end
$var reg 1 5 fl_alloc1 $end
$var reg 1 6 fl_free0 $end
$var reg 1 7 fl_free1 $end
$var reg 7 8 fl_free_reg0 [6:0] $end
$var reg 7 9 fl_free_reg1 [6:0] $end
$var reg 7 : prf_ca0 [6:0] $end
$var reg 7 ; prf_ca1 [6:0] $end
$var reg 1 < prf_cr0 $end
$var reg 1 = prf_cr1 $end
$var reg 7 > prf_ra0 [6:0] $end
$var reg 7 ? prf_ra1 [6:0] $end
$var reg 7 @ prf_ra2 [6:0] $end
$var reg 7 A prf_ra3 [6:0] $end
$var reg 7 B prf_wa0 [6:0] $end
$var reg 7 C prf_wa1 [6:0] $end
$var reg 64 D prf_wd0 [63:0] $end
$var reg 64 E prf_wd1 [63:0] $end
$var reg 1 F prf_we0 $end
$var reg 1 G prf_we1 $end
$var reg 1 H rat_chk $end
$var reg 5 I rat_la0 [4:0] $end
$var reg 5 J rat_la1 [4:0] $end
$var reg 5 K rat_la2 [4:0] $end
$var reg 5 L rat_la3 [4:0] $end
$var reg 5 M rat_ra_a [4:0] $end
$var reg 5 N rat_ra_b [4:0] $end
$var reg 1 O rat_ren_a $end
$var reg 1 P rat_ren_b $end
$var reg 7 Q rat_rp_a [6:0] $end
$var reg 7 R rat_rp_b [6:0] $end
$var reg 1 S rat_rst $end
$var reg 1 T reset $end
$var integer 32 U fail_count [31:0] $end
$var integer 32 V pass_count [31:0] $end
$scope module fl $end
$var wire 1 4 alloc_en0 $end
$var wire 1 5 alloc_en1 $end
$var wire 7 W alloc_reg0 [6:0] $end
$var wire 7 X alloc_reg1 [6:0] $end
$var wire 1 3 clk $end
$var wire 1 6 free_en0 $end
$var wire 1 7 free_en1 $end
$var wire 7 Y free_reg0 [6:0] $end
$var wire 7 Z free_reg1 [6:0] $end
$var wire 1 T reset $end
$var wire 1 1 empty $end
$var wire 8 [ count [7:0] $end
$var wire 1 2 almost_empty $end
$var parameter 32 \ FIFO_DEPTH $end
$var parameter 32 ] PTR_BITS $end
$var reg 8 ^ head [7:0] $end
$var reg 8 _ tail [7:0] $end
$var integer 32 ` i [31:0] $end
$upscope $end
$scope module prf $end
$var wire 7 a clear_ready_addr0 [6:0] $end
$var wire 7 b clear_ready_addr1 [6:0] $end
$var wire 1 < clear_ready_en0 $end
$var wire 1 = clear_ready_en1 $end
$var wire 1 3 clk $end
$var wire 7 c read_addr0 [6:0] $end
$var wire 7 d read_addr1 [6:0] $end
$var wire 7 e read_addr2 [6:0] $end
$var wire 7 f read_addr3 [6:0] $end
$var wire 64 g read_data0 [63:0] $end
$var wire 64 h read_data1 [63:0] $end
$var wire 64 i read_data2 [63:0] $end
$var wire 64 j read_data3 [63:0] $end
$var wire 1 * read_ready0 $end
$var wire 1 ) read_ready1 $end
$var wire 1 ( read_ready2 $end
$var wire 1 ' read_ready3 $end
$var wire 1 T reset $end
$var wire 7 k write_addr0 [6:0] $end
$var wire 7 l write_addr1 [6:0] $end
$var wire 64 m write_data0 [63:0] $end
$var wire 64 n write_data1 [63:0] $end
$var wire 1 F write_en0 $end
$var wire 1 G write_en1 $end
$var integer 32 o i [31:0] $end
$upscope $end
$scope module rat_dut $end
$var wire 1 H checkpoint_en $end
$var wire 1 3 clk $end
$var wire 5 p lookup_arch0 [4:0] $end
$var wire 5 q lookup_arch1 [4:0] $end
$var wire 5 r lookup_arch2 [4:0] $end
$var wire 5 s lookup_arch3 [4:0] $end
$var wire 7 t lookup_phys0 [6:0] $end
$var wire 7 u lookup_phys1 [6:0] $end
$var wire 5 v rename_arch_a [4:0] $end
$var wire 5 w rename_arch_b [4:0] $end
$var wire 1 O rename_en_a $end
$var wire 1 P rename_en_b $end
$var wire 7 x rename_old_a [6:0] $end
$var wire 7 y rename_phys_a [6:0] $end
$var wire 7 z rename_phys_b [6:0] $end
$var wire 1 T reset $end
$var wire 1 S restore_en $end
$var reg 7 { lookup_phys2 [6:0] $end
$var reg 7 | lookup_phys3 [6:0] $end
$var reg 7 } rename_old_b [6:0] $end
$var integer 32 ~ i [31:0] $end
$upscope $end
$scope task check $end
$var reg 64 !" expected [63:0] $end
$var reg 64 "" got [63:0] $end
$var reg 256 #" name [255:0] $end
$upscope $end
$upscope $end
$enddefinitions $end
$comment Show the parameter values. $end
$dumpall
b111 ]
b10000000 \
$end
#0
$dumpvars
bx #"
bx ""
bx !"
b100000 ~
b0 }
b0 |
b0 {
b0 z
b0 y
b0 x
b0 w
b0 v
b0 u
b0 t
b0 s
b0 r
b0 q
b0 p
b10000000 o
b0 n
b0 m
b0 l
b0 k
b0 j
b0 i
b0 h
b0 g
b0 f
b0 e
b0 d
b0 c
b0 b
b0 a
b1100000 `
b1100000 _
b0 ^
b1100000 [
b0 Z
b0 Y
b100001 X
b100000 W
b0 V
b0 U
1T
0S
b0 R
b0 Q
0P
0O
b0 N
b0 M
b0 L
b0 K
b0 J
b0 I
0H
0G
0F
b0 E
b0 D
b0 C
b0 B
b0 A
b0 @
b0 ?
b0 >
0=
0<
b0 ;
b0 :
b0 9
b0 8
07
06
05
04
03
02
01
b100000 0
b100001 /
b0 .
b0 -
b0 ,
b0 +
1*
1)
1(
1'
b0 &
b0 %
b0 $
b0 #
b0 "
b0 !
$end
#5
b1100000 [
b1100000 _
b100000 ~
b10000000 o
b1100000 `
13
#10
03
b1111111 A
b1111111 f
b110010 @
b110010 e
b11111 ?
b11111 d
0T
#11
b11 V
b1110000011100100110011000100000011100100110010101100111001100000010000001110110011000010110110001110101011001010011110100110000 #"
b0 !"
b0 ""
#15
13
#20
b1111101011001110 D
b1111101011001110 m
b101000 B
b101000 k
1F
03
#25
13
#30
b1111101011001110 .
b1111101011001110 g
b101000 >
b101000 c
0F
03
#31
b100 V
b111000001110010011001100010000001110111011100100110100101110100011001010010111101110010011001010110000101100100 #"
b1111101011001110 !"
b1111101011001110 ""
#35
13
#40
b111100 :
b111100 a
1<
03
#45
13
#50
0)
b111100 ?
b111100 d
0<
03
#51
b101 V
b11100000111001001100110001000000110001101101100011001010110000101110010010111110111001001100101011000010110010001111001 #"
b0 !"
b0 ""
#55
13
#60
b1011111011101111 D
b1011111011101111 m
b111100 B
b111100 k
1F
03
#65
1)
b1011111011101111 -
b1011111011101111 h
13
#70
0F
03
#71
b111 V
b1110000011100100110011000100000011101110111001001101001011101000110010100100000011100100110010101110011011101000110111101110010011001010111001100100000011100100110010101100001011001000111100100100000011000100110100101110100 #"
b1 !"
b1 ""
#75
13
#80
b1011101110111011 E
b1011101110111011 n
b1000110 C
b1000110 l
1G
b1010101010101010 D
b1010101010101010 m
b1000110 B
b1000110 k
1F
03
#85
13
#90
b1011101110111011 .
b1011101110111011 g
b1000110 >
b1000110 c
0G
0F
03
#91
b1011 V
b11001100110110000100000011011100110111101110100001000000110010101101101011100000111010001111001 #"
b0 !"
b0 ""
#95
13
#100
15
14
03
#105
b100010 0
b100010 W
b100011 /
b100011 X
b1011110 [
b10 ^
13
#110
05
04
03
#111
b1101 V
b110011001101100001000000110000101100110011101000110010101110010001000000110000101101100011011000110111101100011001100100010000001110010011001010110011100110001001111010011001100110101 #"
b100011 !"
b100011 ""
#115
13
#120
14
03
#125
b100011 0
b100011 W
b100100 /
b100100 X
b1011101 [
b11 ^
13
#130
04
03
#131
b1110 V
b110011001101100001000000110000101100110011101000110010101110010001000000110000101101100011011000110111101100011001100010010000001110010011001010110011100110000001111010011001100110101 #"
#135
13
#140
b100000 8
b100000 Y
16
03
#145
b1011110 [
b1100001 _
13
#150
b1111 #
b1111 |
b11111 $
b11111 {
b101 %
b101 u
b1111 L
b1111 s
b11111 K
b11111 r
b101 J
b101 q
06
03
#151
b10010 V
b11100100110000101110100001000000110100101100100011001010110111001110100011010010111010001111001001000000111001000110001001101010010110100111110011100000011000100110101 #"
b1111 !"
b1111 ""
#155
13
#160
b1 "
b1 x
b110010 Q
b110010 y
b1 M
b1 v
1O
03
#165
b110010 "
b110010 x
13
#170
b110010 &
b110010 t
b1 I
b1 p
0O
03
#171
b10011 V
b1110010011000010111010000100000011100110110100101101110011001110110110001100101001000000111001001100101011011100110000101101101011001010010000001110010001100010010110100111110011100000011010100110000 #"
b110010 !"
b110010 ""
#175
13
#180
b10 "
b10 x
b11 !
b11 }
b1000110 R
b1000110 z
b11 N
b11 w
1P
b111100 Q
b111100 y
b10 M
b10 v
1O
03
#185
b1000110 !
b1000110 }
b111100 "
b111100 x
13
#190
b1000110 %
b1000110 u
b111100 &
b111100 t
b11 J
b11 q
b10 I
b10 p
0P
0O
03
#191
b10101 V
b111001001100001011101000010000001100100011101010110000101101100001000000111001001100101011011100110000101101101011001010010000001110010001100110010110100111110011100000011011100110000 #"
b1000110 !"
b1000110 ""
#195
13
#200
b1010000 Q
b1010000 y
1O
03
#201
b10110 V
b111001001100001011101000010000001101111011011000110010000100000011011010110000101110000011100000110100101101110011001110010000001110010001100100010000001110111011000010111001100100000011100000011011000110000 #"
b111100 !"
b111100 ""
#205
b1010000 &
b1010000 t
b1010000 "
b1010000 x
13
#210
0O
03
#215
13
#220
b101 "
b101 x
b1011010 $
b1011010 {
b101 K
b101 r
b1011010 Q
b1011010 y
b101 M
b101 v
1O
03
#221
b10111 V
b10000001101001011011100111010001110010011000010010110101100111011100100110111101110101011100000010000001100110011101110110010000100000010000100010000001110011011001010110010101110011001000000100000100100000011100100110010101101110011000010110110101100101 #"
b1011010 !"
b1011010 ""
#225
b1011010 "
b1011010 x
13
#230
0O
03
#235
13
#240
b1010 "
b1010 x
b1100100 !
b1100100 }
b1101110 R
b1101110 z
b1010 N
b1010 w
1P
b1100100 Q
b1100100 y
b1010 M
b1010 v
1O
03
#241
b11001 V
b11100100110000101110100001000000110111101101100011001000101111101100010001000000111001000110001001100000010000001101001011100110010000001000001001000000110111001100101011101110010000001110000001100010011000000110000 #"
b1100100 !"
b1100100 ""
#245
b1101110 "
b1101110 x
13
#250
b1101110 &
b1101110 t
b1101110 !
b1101110 }
b1010 I
b1010 p
0P
0O
03
#251
b11010 V
b1110010011000010111010000100000011100100011000100110000001011010011111001110000001100010011000100110000001000000110000101100110011101000110010101110010001000000110010001110101011000010110110000100000011100100110010101101110011000010110110101100101 #"
b1101110 !"
b1101110 ""
#255
13
#260
1H
03
#265
b100000 ~
13
#270
0H
03
#275
13
#280
b0 "
b0 x
b1111000 Q
b1111000 y
b0 M
b0 v
1O
03
#285
b1111000 "
b1111000 x
13
#290
b1111000 &
b1111000 t
b0 I
b0 p
0O
03
#291
b11011 V
b1110010011000010111010000100000011100000110111101110011011101000010110101100011011010000110101100100000011100100110010101101110011000010110110101100101001000000111001000110000001011010011111001110000001100010011001000110000 #"
b1111000 !"
b1111000 ""
#295
13
#300
1S
03
#305
b0 &
b0 t
b0 "
b0 x
b100000 ~
13
#310
0S
03
#311
b1101110 %
b1101110 u
b1010 J
b1010 q
b11100 V
b1110010011000010111010000100000011100100110010101110011011101000110111101110010011001010010000001110010001100000010000001100010011000010110001101101011001000000111010001101111001000000111000000110000 #"
b0 !"
b0 ""
#312
b11101 V
b111001001100001011101000010000001110010011001010111001101110100011011110111001001100101001000000111001000110001001100000010000001110011011101000110100101101100011011000010000001110000001100010011000100110000 #"
b1101110 !"
b1101110 ""
